{
    "token": "b46fa69207f949ae877c525702daea037735af4289c140e90fe480c76f6f635a1574338627966",
    "userId": "3083786518597",
    "name": "葛忆",
    "userDept": "一站式",
    "sex": "1",
    "loginPhone": "15195886747",
    "iomsUrl": "http:\/\/36.152.29.162:50206",
    "baseAppServiceUrl": "http:\/\/hlms.tiansu-china.com",
    "roleMenus": "[{\"menus\":[{\"itemName\":\"安全\",\"itemCode\":\"securityManagement\",\"itemLink\":\"\\\/hlmsApp\\\/index.html\",\"imagePath\":null,\"menuTypeDesc\":\"后勤物业\",\"menuTypeCode\":\"0\",\"buttons\":null,\"source\":\"1\",\"iomsSubsystem\":\"1\",\"status\":1,\"id\":6001,\"parentId\":6000},{\"itemName\":\"质量\",\"itemCode\":\"qualityManagement\",\"itemLink\":\"\\\/hlmsApp\\\/index.html\",\"imagePath\":null,\"menuTypeDesc\":\"后勤物业\",\"menuTypeCode\":\"0\",\"buttons\":null,\"source\":\"1\",\"iomsSubsystem\":\"1\",\"status\":1,\"id\":6002,\"parentId\":6000},{\"itemName\":\"服务\",\"itemCode\":\"serviceManagement\",\"itemLink\":\"\\\/hlmsApp\\\/index.html\",\"imagePath\":null,\"menuTypeDesc\":\"后勤物业\",\"menuTypeCode\":\"0\",\"buttons\":null,\"source\":\"1\",\"iomsSubsystem\":\"1\",\"status\":1,\"id\":6003,\"parentId\":6000},{\"itemName\":\"报表\",\"itemCode\":\"report\",\"itemLink\":\"\\\/hlmsApp\\\/index.html\",\"imagePath\":null,\"menuTypeDesc\":\"后勤物业\",\"menuTypeCode\":\"0\",\"buttons\":null,\"source\":\"1\",\"iomsSubsystem\":\"1\",\"status\":1,\"id\":6004,\"parentId\":6000},{\"itemName\":\"人员\",\"itemCode\":\"personnelManagement\",\"itemLink\":\"\\\/hlmsApp\\\/index.html\",\"imagePath\":null,\"menuTypeDesc\":\"后勤物业\",\"menuTypeCode\":\"0\",\"buttons\":null,\"source\":\"1\",\"iomsSubsystem\":\"1\",\"status\":1,\"id\":6005,\"parentId\":6000},{\"itemName\":\"财务\",\"itemCode\":\"costManagement\",\"itemLink\":\"\\\/hlmsApp\\\/index.html\",\"imagePath\":null,\"menuTypeDesc\":\"后勤物业\",\"menuTypeCode\":\"0\",\"buttons\":null,\"source\":\"1\",\"iomsSubsystem\":\"1\",\"status\":1,\"id\":6006,\"parentId\":6000},{\"itemName\":\"资产\",\"itemCode\":\"assetManagement\",\"itemLink\":\"\\\/hlmsApp\\\/index.html\",\"imagePath\":null,\"menuTypeDesc\":\"后勤物业\",\"menuTypeCode\":\"0\",\"buttons\":null,\"source\":\"1\",\"iomsSubsystem\":\"1\",\"status\":1,\"id\":6007,\"parentId\":6000},{\"itemName\":\"语音助手\",\"itemCode\":\"voiceAssistant\",\"itemLink\":\"\\\/hlmsApp\\\/index.html\",\"imagePath\":null,\"menuTypeDesc\":\"后勤物业\",\"menuTypeCode\":\"0\",\"buttons\":null,\"source\":\"1\",\"iomsSubsystem\":\"1\",\"status\":1,\"id\":6008,\"parentId\":6000}],\"type\":\"module\",\"code\":\"manage\",\"name\":\"一站式管理中心\",\"id\":6000},{\"menus\":[{\"itemName\":\"我要报修\",\"itemCode\":\"507\",\"itemLink\":\"http:\\\/\\\/36.152.29.162:50281\\\/app\\\/static\\\/EAM3.0\\\/index.html\",\"imagePath\":null,\"menuTypeDesc\":\"财务管理\",\"menuTypeCode\":\"2\",\"buttons\":null,\"source\":null,\"iomsSubsystem\":\"1\",\"status\":1,\"id\":42953967927374,\"parentId\":6100},{\"itemName\":\"我要保洁\",\"itemCode\":\"6101\",\"itemLink\":\"\\\/hlmsApp\\\/index.html\",\"imagePath\":null,\"menuTypeDesc\":\"后勤物业\",\"menuTypeCode\":\"0\",\"buttons\":null,\"source\":null,\"iomsSubsystem\":\"1\",\"status\":1,\"id\":6101,\"parentId\":6100},{\"itemName\":\"我要运送\",\"itemCode\":\"6102\",\"itemLink\":null,\"imagePath\":null,\"menuTypeDesc\":\"其他菜单\",\"menuTypeCode\":\"0\",\"buttons\":null,\"source\":null,\"iomsSubsystem\":null,\"status\":0,\"id\":null,\"parentId\":6100},{\"itemName\":\"我的服务\",\"itemCode\":\"5010\",\"itemLink\":\"\\\/hlmsApp\\\/index.html\",\"imagePath\":null,\"menuTypeDesc\":\"后勤物业\",\"menuTypeCode\":\"0\",\"buttons\":null,\"source\":\"1\",\"iomsSubsystem\":\"1\",\"status\":1,\"id\":6103,\"parentId\":6100}],\"type\":\"module\",\"code\":\"service\",\"name\":\"一站式服务中心\",\"id\":6100},{\"menus\":[{\"itemName\":\"通讯录\",\"itemCode\":\"5004\",\"itemLink\":\"\\\/hlmsApp\\\/index.html\",\"imagePath\":null,\"menuTypeDesc\":\"人员管理\",\"menuTypeCode\":\"7\",\"buttons\":null,\"source\":\"1\",\"iomsSubsystem\":\"1\",\"status\":1,\"id\":5042,\"parentId\":5008},{\"itemName\":\"知识库\",\"itemCode\":\"5003\",\"itemLink\":\"\\\/hlmsApp\\\/index.html\",\"imagePath\":null,\"menuTypeDesc\":\"人员管理\",\"menuTypeCode\":\"7\",\"buttons\":null,\"source\":\"1\",\"iomsSubsystem\":\"1\",\"status\":1,\"id\":5041,\"parentId\":5004},{\"itemName\":\"预算管理\",\"itemCode\":\"5005\",\"itemLink\":\"\\\/hlmsApp\\\/index.html\",\"imagePath\":null,\"menuTypeDesc\":\"人员管理\",\"menuTypeCode\":\"7\",\"buttons\":null,\"source\":\"1\",\"iomsSubsystem\":\"1\",\"status\":1,\"id\":5043,\"parentId\":5019},{\"itemName\":\"我的投诉\",\"itemCode\":\"5009\",\"itemLink\":\"\\\/hlmsApp\\\/index.html\",\"imagePath\":null,\"menuTypeDesc\":\"人员管理\",\"menuTypeCode\":\"7\",\"buttons\":null,\"source\":\"1\",\"iomsSubsystem\":\"1\",\"status\":1,\"id\":5952,\"parentId\":5045},{\"itemName\":\"空间设备\",\"itemCode\":\"5006\",\"itemLink\":\"\\\/hlmsApp\\\/index.html\",\"imagePath\":null,\"menuTypeDesc\":\"设备运维\",\"menuTypeCode\":\"3\",\"buttons\":null,\"source\":\"1\",\"iomsSubsystem\":\"1\",\"status\":1,\"id\":5044,\"parentId\":5004},{\"itemName\":\"日常考核\",\"itemCode\":\"5002\",\"itemLink\":\"\\\/hlmsApp\\\/index.html\",\"imagePath\":null,\"menuTypeDesc\":\"人员管理\",\"menuTypeCode\":\"7\",\"buttons\":null,\"source\":\"1\",\"iomsSubsystem\":\"1\",\"status\":1,\"id\":5011,\"parentId\":5008}],\"type\":\"module\",\"code\":\"maintenance\",\"name\":\"一站式运维中心\",\"id\":6200}]",
    "subsystemno": "",
    "subsystemname": "",
    "subsystemhost": "",
    "scanResult": "",
    "htmlUrl": "",
    "head": "",
    "subtypeId": "0",
    "subtypeName": "",
    "msgId": "",
    "msgType": "",
    "type": "dailyreport",
    "tenantId": "718",
    "typeName": "",
    "moduleinfo": "",
    "pushInfo": "",
    "isPush": "",
    "loginInfo": "{\"success\":true,\"exceptionMsg\":\"成功\",\"excuteDateTime\":\"2019-11-21 20:17:08 219\",\"resultBody\":{\"token\":\"b46fa69207f949ae877c525702daea037735af4289c140e90fe480c76f6f635a1574338627966\",\"userId\":\"3083786518597\",\"loginName\":\"xuya\",\"name\":\"吴俊慧\",\"roles\":[{\"roleno\":\"3083786518529\",\"rolename\":\"对接全部子系统系统管理员\",\"rolecode\":\"SPECIAL_CMANAGER\"},{\"roleno\":\"3083786518533\",\"rolename\":\"东院区\",\"rolecode\":\"YYFQ1\"},{\"roleno\":\"3083786518534\",\"rolename\":\"西院区\",\"rolecode\":\"YYFQ2\"},{\"roleno\":\"3083786518535\",\"rolename\":\"南院区\",\"rolecode\":\"YYFQ3\"},{\"roleno\":\"3083786518536\",\"rolename\":\"北院区\",\"rolecode\":\"YYFQ4\"},{\"roleno\":\"3083786518566\",\"rolename\":\"应急保洁主管\",\"rolecode\":\"EMERGENCY_CMANAGER\"},{\"roleno\":\"3083786518567\",\"rolename\":\"专项保洁主管\",\"rolecode\":\"SPECIAL_CMANAGER\"},{\"roleno\":\"3083786518573\",\"rolename\":\"专项保洁员\",\"rolecode\":\"SPECIAL_CWORKER\"}],\"sex\":\"1\",\"loginPhone\":\"15195886747\",\"byPhone\":\"\",\"subSystems\":[{\"menus\":[{\"itemName\":\"二维码配置\",\"itemCode\":\"5001\",\"itemLink\":\"\/hlmsApp\/index.html\",\"imagePath\":null,\"menuTypeDesc\":\"公共功能\",\"menuTypeCode\":\"5\",\"buttons\":null,\"source\":\"1\",\"iomsSubsystem\":\"1\",\"status\":1,\"id\":null,\"parentId\":null},{\"itemName\":\"日常考核\",\"itemCode\":\"5002\",\"itemLink\":\"\/hlmsApp\/index.html\",\"imagePath\":null,\"menuTypeDesc\":\"人员管理\",\"menuTypeCode\":\"7\",\"buttons\":null,\"source\":\"1\",\"iomsSubsystem\":\"1\",\"status\":1,\"id\":null,\"parentId\":null},{\"itemName\":\"知识库\",\"itemCode\":\"5003\",\"itemLink\":\"\/hlmsApp\/index.html\",\"imagePath\":null,\"menuTypeDesc\":\"人员管理\",\"menuTypeCode\":\"7\",\"buttons\":null,\"source\":\"1\",\"iomsSubsystem\":\"1\",\"status\":1,\"id\":null,\"parentId\":null},{\"itemName\":\"通讯录\",\"itemCode\":\"5004\",\"itemLink\":\"\/hlmsApp\/index.html\",\"imagePath\":null,\"menuTypeDesc\":\"人员管理\",\"menuTypeCode\":\"7\",\"buttons\":null,\"source\":\"1\",\"iomsSubsystem\":\"1\",\"status\":1,\"id\":null,\"parentId\":null},{\"itemName\":\"预算管理\",\"itemCode\":\"5005\",\"itemLink\":\"\/hlmsApp\/index.html\",\"imagePath\":null,\"menuTypeDesc\":\"人员管理\",\"menuTypeCode\":\"7\",\"buttons\":null,\"source\":\"1\",\"iomsSubsystem\":\"1\",\"status\":1,\"id\":null,\"parentId\":null},{\"itemName\":\"空间设备\",\"itemCode\":\"5006\",\"itemLink\":\"\/hlmsApp\/index.html\",\"imagePath\":null,\"menuTypeDesc\":\"设备运维\",\"menuTypeCode\":\"3\",\"buttons\":null,\"source\":\"1\",\"iomsSubsystem\":\"1\",\"status\":1,\"id\":null,\"parentId\":null},{\"itemName\":\"我的投诉\",\"itemCode\":\"5009\",\"itemLink\":\"\/hlmsApp\/index.html\",\"imagePath\":null,\"menuTypeDesc\":\"人员管理\",\"menuTypeCode\":\"7\",\"buttons\":null,\"source\":\"1\",\"iomsSubsystem\":\"1\",\"status\":1,\"id\":null,\"parentId\":null},{\"itemName\":\"考勤统计\",\"itemCode\":\"5101\",\"itemLink\":\"\/app\/static\/PAM\/index.html\",\"imagePath\":null,\"menuTypeDesc\":\"人员管理\",\"menuTypeCode\":\"7\",\"buttons\":null,\"source\":\"1\",\"iomsSubsystem\":\"1\",\"status\":1,\"id\":null,\"parentId\":null},{\"itemName\":\"考勤打卡\",\"itemCode\":\"5102\",\"itemLink\":\"\/app\/static\/PAM\/index.html\",\"imagePath\":null,\"menuTypeDesc\":\"人员管理\",\"menuTypeCode\":\"7\",\"buttons\":null,\"source\":\"1\",\"iomsSubsystem\":\"1\",\"status\":1,\"id\":null,\"parentId\":null},{\"itemName\":\"我的保洁\",\"itemCode\":\"5007\",\"itemLink\":\"hlmsApp\/index.html\",\"imagePath\":null,\"menuTypeDesc\":\"后勤物业\",\"menuTypeCode\":\"0\",\"buttons\":null,\"source\":\"1\",\"iomsSubsystem\":\"1\",\"status\":1,\"id\":null,\"parentId\":null},{\"itemName\":\"保洁查询\",\"itemCode\":\"5008\",\"itemLink\":\"hlmsApp\/index.html\",\"imagePath\":null,\"menuTypeDesc\":\"后勤物业\",\"menuTypeCode\":\"0\",\"buttons\":null,\"source\":\"1\",\"iomsSubsystem\":\"1\",\"status\":1,\"id\":null,\"parentId\":null},{\"itemName\":\"中央运送\",\"itemCode\":\"1531702650909564\",\"itemLink\":\"http:\/\/36.152.29.162:50206\/connect\/oauth2\/authorize?appid=716&redirect_uri=http:\/\/119.23.253.133:9090\/delivery\/interfaces\/loginCallback.do?showtype=APP&response_type=code&scope=snsapi_userinfo&agentid=1531702650909564&state=640424&APPType=native\",\"imagePath\":null,\"menuTypeDesc\":\"能源管理\",\"menuTypeCode\":\"1\",\"buttons\":null,\"source\":\"2\",\"iomsSubsystem\":\"0\",\"status\":1,\"id\":null,\"parentId\":null},{\"itemName\":\"我要报修\",\"itemCode\":\"507\",\"itemLink\":\"http:\/\/36.152.29.162:50281\/app\/static\/EAM3.0\/index.html\",\"imagePath\":null,\"menuTypeDesc\":\"财务管理\",\"menuTypeCode\":\"2\",\"buttons\":null,\"source\":\"1\",\"iomsSubsystem\":\"1\",\"status\":1,\"id\":null,\"parentId\":null},{\"itemName\":\"我的报修\",\"itemCode\":\"508\",\"itemLink\":\"http:\/\/36.152.29.162:50281\/app\/static\/EAM3.0\/index.html\",\"imagePath\":null,\"menuTypeDesc\":\"设备运维\",\"menuTypeCode\":\"3\",\"buttons\":null,\"source\":\"1\",\"iomsSubsystem\":\"1\",\"status\":1,\"id\":null,\"parentId\":null},{\"itemName\":\"我的工单\",\"itemCode\":\"510\",\"itemLink\":\"http:\/\/36.152.29.162:50281\/app\/static\/EAM3.0\/index.html\",\"imagePath\":null,\"menuTypeDesc\":\"设备运维\",\"menuTypeCode\":\"3\",\"buttons\":null,\"source\":\"1\",\"iomsSubsystem\":\"1\",\"status\":1,\"id\":null,\"parentId\":null},{\"itemName\":\"我的巡检\",\"itemCode\":\"512\",\"itemLink\":\"http:\/\/36.152.29.162:50281\/app\/static\/EAM3.0\/index.html\",\"imagePath\":null,\"menuTypeDesc\":\"设备运维\",\"menuTypeCode\":\"3\",\"buttons\":null,\"source\":\"1\",\"iomsSubsystem\":\"1\",\"status\":1,\"id\":null,\"parentId\":null},{\"itemName\":\"我的保养\",\"itemCode\":\"514\",\"itemLink\":\"http:\/\/36.152.29.162:50281\/app\/static\/EAM3.0\/index.html\",\"imagePath\":null,\"menuTypeDesc\":\"设备运维\",\"menuTypeCode\":\"3\",\"buttons\":null,\"source\":\"1\",\"iomsSubsystem\":\"1\",\"status\":1,\"id\":null,\"parentId\":null},{\"itemName\":\"工单查询\",\"itemCode\":\"518\",\"itemLink\":\"http:\/\/36.152.29.162:50281\/app\/static\/EAM3.0\/index.html\",\"imagePath\":null,\"menuTypeDesc\":\"设备运维\",\"menuTypeCode\":\"3\",\"buttons\":null,\"source\":\"1\",\"iomsSubsystem\":\"1\",\"status\":1,\"id\":null,\"parentId\":null},{\"itemName\":\"报修统计\",\"itemCode\":\"519\",\"itemLink\":\"http:\/\/36.152.29.162:50281\/app\/static\/EAM3.0\/index.html\",\"imagePath\":null,\"menuTypeDesc\":\"设备运维\",\"menuTypeCode\":\"3\",\"buttons\":null,\"source\":\"1\",\"iomsSubsystem\":\"1\",\"status\":1,\"id\":null,\"parentId\":null},{\"itemName\":\"值班记录\",\"itemCode\":\"542\",\"itemLink\":\"http:\/\/36.152.29.162:50281\/app\/static\/EAM3.0\/index.html\",\"imagePath\":null,\"menuTypeDesc\":\"设备运维\",\"menuTypeCode\":\"3\",\"buttons\":null,\"source\":\"1\",\"iomsSubsystem\":\"1\",\"status\":1,\"id\":null,\"parentId\":null},{\"itemName\":\"巡检查询\",\"itemCode\":\"520\",\"itemLink\":\"http:\/\/36.152.29.162:50281\/app\/static\/EAM3.0\/index.html\",\"imagePath\":null,\"menuTypeDesc\":\"设备运维\",\"menuTypeCode\":\"3\",\"buttons\":null,\"source\":\"1\",\"iomsSubsystem\":\"1\",\"status\":1,\"id\":null,\"parentId\":null},{\"itemName\":\"保养查询\",\"itemCode\":\"521\",\"itemLink\":\"http:\/\/36.152.29.162:50281\/app\/static\/EAM3.0\/index.html\",\"imagePath\":null,\"menuTypeDesc\":\"设备运维\",\"menuTypeCode\":\"3\",\"buttons\":null,\"source\":\"1\",\"iomsSubsystem\":\"1\",\"status\":1,\"id\":null,\"parentId\":null},{\"itemName\":\"突发事件\",\"itemCode\":\"541\",\"itemLink\":\"http:\/\/36.152.29.162:50281\/app\/static\/EAM3.0\/index.html\",\"imagePath\":null,\"menuTypeDesc\":\"安全管理\",\"menuTypeCode\":\"6\",\"buttons\":null,\"source\":\"1\",\"iomsSubsystem\":\"1\",\"status\":1,\"id\":null,\"parentId\":null},{\"itemName\":\"保养统计\",\"itemCode\":\"538\",\"itemLink\":\"http:\/\/36.152.29.162:50281\/app\/static\/EAM3.0\/index.html\",\"imagePath\":null,\"menuTypeDesc\":\"设备运维\",\"menuTypeCode\":\"3\",\"buttons\":null,\"source\":\"1\",\"iomsSubsystem\":\"1\",\"status\":1,\"id\":null,\"parentId\":null},{\"itemName\":\"巡检统计\",\"itemCode\":\"539\",\"itemLink\":\"http:\/\/36.152.29.162:50281\/app\/static\/EAM3.0\/index.html\",\"imagePath\":null,\"menuTypeDesc\":\"设备运维\",\"menuTypeCode\":\"3\",\"buttons\":null,\"source\":\"1\",\"iomsSubsystem\":\"1\",\"status\":1,\"id\":null,\"parentId\":null},{\"itemName\":\"维修质量\",\"itemCode\":\"540\",\"itemLink\":\"http:\/\/36.152.29.162:50281\/app\/static\/EAM3.0\/index.html\",\"imagePath\":null,\"menuTypeDesc\":\"设备运维\",\"menuTypeCode\":\"3\",\"buttons\":null,\"source\":\"1\",\"iomsSubsystem\":\"1\",\"status\":1,\"id\":null,\"parentId\":null},{\"itemName\":\"耗材分析\",\"itemCode\":\"5201\",\"itemLink\":\"http:\/\/36.152.29.162:50281\/app\/static\/EAM3.0\/index.html\",\"imagePath\":null,\"menuTypeDesc\":\"设备运维\",\"menuTypeCode\":\"3\",\"buttons\":null,\"source\":\"1\",\"iomsSubsystem\":\"1\",\"status\":1,\"id\":null,\"parentId\":null},{\"itemName\":\"能耗分析\",\"itemCode\":\"502\",\"itemLink\":\"http:\/\/36.152.29.162:50161\/apphtml\/index.htm\",\"imagePath\":null,\"menuTypeDesc\":\"能源管理\",\"menuTypeCode\":\"1\",\"buttons\":null,\"source\":\"1\",\"iomsSubsystem\":\"1\",\"status\":1,\"id\":null,\"parentId\":null},{\"itemName\":\"KPI管理\",\"itemCode\":\"503\",\"itemLink\":\"http:\/\/36.152.29.162:50161\/apphtml\/index.htm\",\"imagePath\":null,\"menuTypeDesc\":\"能源管理\",\"menuTypeCode\":\"1\",\"buttons\":null,\"source\":\"1\",\"iomsSubsystem\":\"1\",\"status\":1,\"id\":null,\"parentId\":null},{\"itemName\":\"告警管理\",\"itemCode\":\"504\",\"itemLink\":\"http:\/\/36.152.29.162:50161\/apphtml\/index.htm\",\"imagePath\":null,\"menuTypeDesc\":\"安全管理\",\"menuTypeCode\":\"6\",\"buttons\":null,\"source\":\"1\",\"iomsSubsystem\":\"1\",\"status\":1,\"id\":null,\"parentId\":null},{\"itemName\":\"能耗纵览\",\"itemCode\":\"523\",\"itemLink\":\"http:\/\/36.152.29.162:50161\/apphtml\/index.htm\",\"imagePath\":null,\"menuTypeDesc\":\"能源管理\",\"menuTypeCode\":\"1\",\"buttons\":null,\"source\":\"1\",\"iomsSubsystem\":\"1\",\"status\":1,\"id\":null,\"parentId\":null},{\"itemName\":\"手术室\",\"itemCode\":\"524\",\"itemLink\":\"IMSAPP\/index.htm\",\"imagePath\":null,\"menuTypeDesc\":\"设备监控\",\"menuTypeCode\":\"4\",\"buttons\":null,\"source\":\"1\",\"iomsSubsystem\":\"1\",\"status\":1,\"id\":null,\"parentId\":null},{\"itemName\":\"变配电\",\"itemCode\":\"532\",\"itemLink\":\"IMSAPP\/index.htm\",\"imagePath\":null,\"menuTypeDesc\":\"设备监控\",\"menuTypeCode\":\"4\",\"buttons\":null,\"source\":\"1\",\"iomsSubsystem\":\"1\",\"status\":1,\"id\":null,\"parentId\":null},{\"itemName\":\"暖通空调\",\"itemCode\":\"533\",\"itemLink\":\"IMSAPP\/index.htm\",\"imagePath\":null,\"menuTypeDesc\":\"设备监控\",\"menuTypeCode\":\"4\",\"buttons\":null,\"source\":\"1\",\"iomsSubsystem\":\"1\",\"status\":1,\"id\":null,\"parentId\":null},{\"itemName\":\"给排水\",\"itemCode\":\"534\",\"itemLink\":\"IMSAPP\/index.htm\",\"imagePath\":null,\"menuTypeDesc\":\"设备监控\",\"menuTypeCode\":\"4\",\"buttons\":null,\"source\":\"1\",\"iomsSubsystem\":\"1\",\"status\":1,\"id\":null,\"parentId\":null},{\"itemName\":\"电梯\",\"itemCode\":\"535\",\"itemLink\":\"IMSAPP\/index.htm\",\"imagePath\":null,\"menuTypeDesc\":\"设备监控\",\"menuTypeCode\":\"4\",\"buttons\":null,\"source\":\"1\",\"iomsSubsystem\":\"1\",\"status\":1,\"id\":null,\"parentId\":null},{\"itemName\":\"医用气体\",\"itemCode\":\"536\",\"itemLink\":\"IMSAPP\/index.htm\",\"imagePath\":null,\"menuTypeDesc\":\"设备监控\",\"menuTypeCode\":\"4\",\"buttons\":null,\"source\":\"1\",\"iomsSubsystem\":\"1\",\"status\":1,\"id\":null,\"parentId\":null},{\"itemName\":\"冰箱\",\"itemCode\":\"5401\",\"itemLink\":\"IMSAPP\/index.htm\",\"imagePath\":null,\"menuTypeDesc\":\"设备监控\",\"menuTypeCode\":\"4\",\"buttons\":null,\"source\":\"1\",\"iomsSubsystem\":\"1\",\"status\":1,\"id\":null,\"parentId\":null},{\"itemName\":\"环境\",\"itemCode\":\"5402\",\"itemLink\":\"IMSAPP\/index.htm\",\"imagePath\":null,\"menuTypeDesc\":\"设备监控\",\"menuTypeCode\":\"4\",\"buttons\":null,\"source\":\"1\",\"iomsSubsystem\":\"1\",\"status\":1,\"id\":null,\"parentId\":null},{\"itemName\":\"智能照明\",\"itemCode\":\"5403\",\"itemLink\":\"IMSAPP\/index.htm\",\"imagePath\":null,\"menuTypeDesc\":\"设备监控\",\"menuTypeCode\":\"4\",\"buttons\":null,\"source\":\"1\",\"iomsSubsystem\":\"1\",\"status\":1,\"id\":null,\"parentId\":null},{\"itemName\":\"视频监控\",\"itemCode\":\"5404\",\"itemLink\":\"IMSAPP\/index.htm\",\"imagePath\":null,\"menuTypeDesc\":\"设备监控\",\"menuTypeCode\":\"4\",\"buttons\":null,\"source\":\"1\",\"iomsSubsystem\":\"1\",\"status\":1,\"id\":null,\"parentId\":null}],\"subsystemno\":\"hlms\",\"subsystemname\":\"hlms\",\"subsystemhost\":\"\"}],\"userDept\":\"一站式\",\"tenantId\":\"718\",\"containPush\":true,\"onesiteTel\":\"23123123\",\"passwordFlag\":\"0\",\"multiCampus\":true,\"usable\":[{\"item\":\"campus\",\"values\":[{\"code\":\"YYBM01\",\"name\":\"本溪基地\"},{\"code\":\"YYBM02\",\"name\":\"滑翔院区\"},{\"code\":\"YYBM03\",\"name\":\"南湖院区\"},{\"code\":\"TSYY01\",\"name\":\"沈北院区\"}]}],\"used\":[{\"item\":\"campus\",\"code\":\"SJHOBX,SJHOHX,SJHOSB,SJHONH\"}],\"hospitalLeader\":true}}",
    "fontScale": "1",
    "entrance": "",
    "newsField": ""
}